ngm_salam/__init__.py
ngm_salam/__main__.py
ngm_salam/message.py
ngm_salam/sysparams.py
ngm_salam-0.0.10.dist-info/METADATA
ngm_salam-0.0.10.dist-info/WHEEL
ngm_salam-0.0.10.dist-info/entry_points.txt
ngm_salam-0.0.10.dist-info/top_level.txt
ngm_salam-0.0.10.dist-info/RECORD
