Metadata-Version: 2.1
Name: ngm-salam
Version: 0.0.10
Summary: Just a demo project
Project-URL: Homepage, https://github.com/ngmaibulat/training-python-packaging
Project-URL: Documentation, https://github.com/ngmaibulat/training-python-packaging
Project-URL: Changes, https://github.com/ngmaibulat/training-python-packaging
Keywords: sample,project
Requires-Python: >=3.8
Requires-Dist: requests
Requires-Dist: psutil
